celery_gsheets/__init__.py
celery_gsheets/celery.py
celery_gsheets/pygsheets.py
celery_gsheets/tasks.py
celery_gsheets-0.1.0.dist-info/LICENSE
celery_gsheets-0.1.0.dist-info/WHEEL
celery_gsheets-0.1.0.dist-info/METADATA
celery_gsheets-0.1.0.dist-info/RECORD
