Metadata-Version: 2.1
Name: celery-gsheets
Version: 0.1.0
Summary: A celery package for gsheets
Author: David Jeong
Author-email: drumrobot@1do.space
Requires-Python: >=3.8,<4.0
Classifier: Programming Language :: Python :: 3
Classifier: Programming Language :: Python :: 3.10
Classifier: Programming Language :: Python :: 3.8
Classifier: Programming Language :: Python :: 3.9
Requires-Dist: celery (>=5.2.7,<6.0.0)
Requires-Dist: pygsheets (>=2.0.5,<3.0.0)
Requires-Dist: python-decouple (>=3.6,<4.0)
Requires-Dist: redis (>=4.3.4,<5.0.0)
Project-URL: Bug Tracker, https://github.com/ODCNC/celery-gsheets/issues
Project-URL: Homepage, https://github.com/ODCNC/celery-gsheets
